{
    "demo-01": {
        "title": "Demo Main",
        "demo_url": "https://adot.thimpress.com/",
        "thumbnail_url": "http://adot.thimpress.com/wp-content/uploads/2020/08/demo-01.jpg"
    },
    "demo-02": {
        "title": "Demo 02",
        "demo_url": "https://adot.thimpress.com/home-02/",
        "thumbnail_url": "http://adot.thimpress.com/wp-content/uploads/2020/08/demo-02.jpg"
    },
    "demo-03": {
        "title": "Demo 03",
        "demo_url": "https://adot.thimpress.com/home-03/",
        "thumbnail_url": "http://adot.thimpress.com/wp-content/uploads/2020/08/demo-03.jpg"
    },
    "demo-04": {
        "title": "Demo 04",
        "demo_url": "https://adot.thimpress.com/home-04/",
        "thumbnail_url": "http://adot.thimpress.com/wp-content/uploads/2020/08/demo-04.jpg"
    },
    "demo-05": {
        "title": "Demo 05",
        "demo_url": "https://adot.thimpress.com/home-05/",
        "thumbnail_url": "http://adot.thimpress.com/wp-content/uploads/2020/08/demo-05.jpg"
    },
    "demo-06": {
        "title": "Demo 06",
        "demo_url": "https://adot.thimpress.com/home-06/",
        "thumbnail_url": "http://adot.thimpress.com/wp-content/uploads/2020/08/demo-06.jpg"
    },
    "demo-07": {
        "title": "Demo 07",
        "demo_url": "https://adot.thimpress.com/home-07/",
        "thumbnail_url": "http://adot.thimpress.com/wp-content/uploads/2020/08/demo-07.jpg"
    },
    "demo-08": {
        "title": "Demo 08",
        "demo_url": "https://adot.thimpress.com/home-08/",
        "thumbnail_url": "http://adot.thimpress.com/wp-content/uploads/2020/08/demo-08.jpg"
    },
    "demo-09": {
        "title": "Demo 09",
        "demo_url": "https://adot.thimpress.com/home-09/",
        "thumbnail_url": "http://adot.thimpress.com/wp-content/uploads/2020/08/demo-09.jpg"
    }
}